zwimage/__init__.py
zwimage/__version__.py
zwimage-0.0.1.dist-info/LICENSE
zwimage-0.0.1.dist-info/METADATA
zwimage-0.0.1.dist-info/WHEEL
zwimage-0.0.1.dist-info/top_level.txt
zwimage-0.0.1.dist-info/RECORD
